batorch/__init__.py
batorch/device.py
batorch/optimizer.py
batorch/tensor.py
batorch/tensor_generator.py
batorch/tensor_template.py
batorch/tensorfunc.py
batorch/tensorsize.py
micomputing/__init__.py
micomputing/data.py
micomputing/funcs.py
micomputing/metrics.py
micomputing/micfunctions.so
micomputing/network.py
micomputing/plot.py
micomputing/stdio.py
micomputing/test_dismap.py
micomputing/trans.py
micomputing/zxhtools/TRS.py
micomputing/zxhtools/exec.py
micomputing/zxhtools/image2.AFF
micomputing/zxhtools/image2.FFD
micomputing/zxhtools/__pycache__/AFF.cpython-39.pyc
micomputing/zxhtools/__pycache__/FFD.cpython-39.pyc
micomputing/zxhtools/__pycache__/TRS.cpython-311.pyc
micomputing/zxhtools/__pycache__/TRS.cpython-37.pyc
micomputing/zxhtools/__pycache__/TRS.cpython-39.pyc
micomputing/zxhtools/__pycache__/exec.cpython-311.pyc
batorch-1.0.55.dist-info/METADATA
batorch-1.0.55.dist-info/WHEEL
batorch-1.0.55.dist-info/top_level.txt
batorch-1.0.55.dist-info/RECORD
